ores/__init__.py
ores/about.py
ores/api.py
ores/errors.py
ores/ores.py
ores/score_request.py
ores/score_response.py
ores/scoring_context.py
ores/util.py
ores/applications/__init__.py
ores/applications/celery.py
ores/applications/util.py
ores/applications/wsgi.py
ores/lock_manager/__init__.py
ores/lock_manager/ip_range_list.py
ores/lock_manager/lock_manager.py
ores/lock_manager/poolcounter.py
ores/logging/__init__.py
ores/logging/logstash_fomatter.py
ores/logging/logstash_handler.py
ores/metrics_collectors/__init__.py
ores/metrics_collectors/logger.py
ores/metrics_collectors/metrics_collector.py
ores/metrics_collectors/null.py
ores/metrics_collectors/statsd.py
ores/metrics_collectors/util.py
ores/score_caches/__init__.py
ores/score_caches/empty.py
ores/score_caches/lru.py
ores/score_caches/redis.py
ores/score_caches/score_cache.py
ores/scoring/__init__.py
ores/scoring/models/__init__.py
ores/scoring/models/rev_id_scorer.py
ores/scoring_systems/__init__.py
ores/scoring_systems/celery_queue.py
ores/scoring_systems/process_pool.py
ores/scoring_systems/scoring_system.py
ores/scoring_systems/single_thread.py
ores/task_tracker/__init__.py
ores/task_tracker/in_memory_task_tracker.py
ores/task_tracker/null_task_tracker.py
ores/task_tracker/redis_task_tracker.py
ores/task_tracker/task_tracker.py
ores/utilities/__init__.py
ores/utilities/precached.py
ores/utilities/score_revisions.py
ores/utilities/stress_test.py
ores/utilities/test_api.py
ores/utilities/util.py
ores/wsgi/__init__.py
ores/wsgi/preprocessors.py
ores/wsgi/responses.py
ores/wsgi/server.py
ores/wsgi/util.py
ores/wsgi/routes/__init__.py
ores/wsgi/routes/ui.py
ores/wsgi/routes/versions.py
ores/wsgi/routes/v1/__init__.py
ores/wsgi/routes/v1/scores.py
ores/wsgi/routes/v1/spec.py
ores/wsgi/routes/v1/util.py
ores/wsgi/routes/v2/__init__.py
ores/wsgi/routes/v2/precache.py
ores/wsgi/routes/v2/scores.py
ores/wsgi/routes/v2/spec.py
ores/wsgi/routes/v2/util.py
ores/wsgi/routes/v3/__init__.py
ores/wsgi/routes/v3/precache.py
ores-1.4.0.dist-info/LICENSE
ores-1.4.0.dist-info/METADATA
ores-1.4.0.dist-info/WHEEL
ores-1.4.0.dist-info/entry_points.txt
ores-1.4.0.dist-info/top_level.txt
ores-1.4.0.dist-info/RECORD
