Metadata-Version: 2.1
Name: ores
Version: 1.4.0
Summary: A webserver for hosting scorer models.
Home-page: https://github.com/wikimedia/ores
Author: Aaron Halfaker
Author-email: ahalfaker@wikimedia.org
License: MIT
Platform: UNKNOWN
Classifier: Development Status :: 3 - Alpha
Classifier: Programming Language :: Python
Classifier: Programming Language :: Python :: 3
Classifier: Environment :: Other Environment
Classifier: Intended Audience :: Developers
Classifier: License :: OSI Approved :: MIT License
Classifier: Operating System :: OS Independent
Requires-Python: >=3
Requires-Dist: celery (<4.1.999,>=4.1.1)
Requires-Dist: docopt (<0.6.999,>=0.6.2)
Requires-Dist: flask (<1.0.999,>=1.0.2)
Requires-Dist: flask-jsonpify (<1.5.999,>=1.5.0)
Requires-Dist: flask-swaggerui (<0.0.999,>=0.0.1)
Requires-Dist: flask-wikimediaui (<0.0.999,>=0.0.1)
Requires-Dist: mwapi (<0.5.999,>=0.5.0)
Requires-Dist: pyyaml (==4.2b4)
Requires-Dist: redis (<4.0.0,>=3.2.1)
Requires-Dist: revscoring (<2.6.999,>=2.3.0)
Requires-Dist: sseclient (>=0.0.18)
Requires-Dist: stopit (<1.1.999,>=1.1.1)
Requires-Dist: werkzeug (==0.16.1)
Requires-Dist: yamlconf (<0.2.999,>=0.2.4)
Provides-Extra: redis
Requires-Dist: pylru ; extra == 'redis'
Requires-Dist: redis ; extra == 'redis'
